trs80tag/__init__.py
trs80tag/__main__.py
trs80tag/coco_raaka_tu.bin
trs80tag/coco_raaka_tu.py
trs80tag-1.10.1.dist-info/LICENSE
trs80tag-1.10.1.dist-info/METADATA
trs80tag-1.10.1.dist-info/WHEEL
trs80tag-1.10.1.dist-info/top_level.txt
trs80tag-1.10.1.dist-info/RECORD
