Metadata-Version: 2.1
Name: trs80tag
Version: 1.10.1
Summary: Classic text adventures from the CoCo and TRS80 Model 1
Home-page: https://github.com/topherCantrell/trs80tag
Author: Chris Cantrell
Author-email: topherCantrell@gmail.com
License: UNKNOWN
Platform: UNKNOWN
Classifier: Programming Language :: Python :: 3
Classifier: License :: OSI Approved :: MIT License
Classifier: Operating System :: OS Independent
Requires-Python: >=3.6
Requires-Dist: MC6809
